ginga/AstroImage.py
ginga/AutoCuts.py
ginga/BaseImage.py
ginga/Bindings.py
ginga/ColorDist.py
ginga/GingaPlugin.py
ginga/ImageView.py
ginga/LayerImage.py
ginga/Mixins.py
ginga/RGBImage.py
ginga/RGBMap.py
ginga/__init__.py
ginga/cmap.py
ginga/colors.py
ginga/events.py
ginga/imap.py
ginga/toolkit.py
ginga/trcalc.py
ginga/version.py
ginga/zoom.py
ginga/aggw/AggHelp.py
ginga/aggw/CanvasRenderAgg.py
ginga/aggw/ImageViewAgg.py
ginga/aggw/Plot.py
ginga/aggw/Widgets.py
ginga/aggw/__init__.py
ginga/cairow/CairoHelp.py
ginga/cairow/CanvasRenderCairo.py
ginga/cairow/ImageViewCairo.py
ginga/cairow/__init__.py
ginga/canvas/CanvasMixin.py
ginga/canvas/CanvasObject.py
ginga/canvas/CompoundMixin.py
ginga/canvas/DrawingMixin.py
ginga/canvas/__init__.py
ginga/canvas/coordmap.py
ginga/canvas/mixins.py
ginga/canvas/render.py
ginga/canvas/transform.py
ginga/canvas/types/__init__.py
ginga/canvas/types/all.py
ginga/canvas/types/astro.py
ginga/canvas/types/basic.py
ginga/canvas/types/image.py
ginga/canvas/types/layer.py
ginga/canvas/types/mixins.py
ginga/canvas/types/plots.py
ginga/canvas/types/utils.py
ginga/cursors/__init__.py
ginga/cursors/cross.svg
ginga/cursors/cursor_info.py
ginga/cursors/cursors.toml
ginga/cursors/hand.svg
ginga/cursors/magnify.svg
ginga/cursors/pencil.svg
ginga/cvw/CanvasRenderCv.py
ginga/cvw/CvHelp.py
ginga/cvw/ImageViewCv.py
ginga/cvw/__init__.py
ginga/doc/__init__.py
ginga/doc/download_doc.py
ginga/doc/help.html
ginga/examples/bindings/bindings.cfg.ds9
ginga/examples/bindings/bindings.cfg.standard
ginga/examples/bindings/bindings.cfg.trackpad
ginga/examples/bokeh/example1.py
ginga/examples/configs/channel_Image.cfg
ginga/examples/configs/general.cfg
ginga/examples/configs/mime.types
ginga/examples/configs/plugin_AutoLoad.cfg
ginga/examples/configs/plugin_Blink.cfg
ginga/examples/configs/plugin_Catalogs.cfg
ginga/examples/configs/plugin_ChangeHistory.cfg
ginga/examples/configs/plugin_Collage.cfg
ginga/examples/configs/plugin_ColorMapPicker.cfg
ginga-5.5.1.dist-info/licenses/LICENSE.txt
ginga-5.5.1.dist-info/METADATA
ginga-5.5.1.dist-info/WHEEL
ginga-5.5.1.dist-info/entry_points.txt
ginga-5.5.1.dist-info/top_level.txt
ginga-5.5.1.dist-info/RECORD
