Metadata-Version: 2.4
Name: ginga
Version: 5.5.1
Summary: A scientific image viewer and toolkit
Home-page: https://ejeschke.github.io/ginga/
Author: Ginga Maintainers
Author-email: eric@naoj.org
License: BSD
Keywords: scientific,image,viewer,numpy,toolkit,astronomy,FITS
Classifier: Intended Audience :: Science/Research
Classifier: License :: OSI Approved :: BSD License
Classifier: Operating System :: MacOS :: MacOS X
Classifier: Operating System :: Microsoft :: Windows
Classifier: Operating System :: POSIX
Classifier: Programming Language :: C
Classifier: Programming Language :: Python :: 3.11
Classifier: Programming Language :: Python :: 3.12
Classifier: Programming Language :: Python :: 3.13
Classifier: Programming Language :: Python :: 3
Classifier: Topic :: Scientific/Engineering :: Astronomy
Classifier: Topic :: Scientific/Engineering :: Physics
Requires-Python: >=3.11
License-File: LICENSE.txt
Requires-Dist: numpy>=1.26
Requires-Dist: qtpy>=2.4.1
Requires-Dist: astropy>=6.0.1
Requires-Dist: puremagic>=1.28
Requires-Dist: pillow>=11.1.0
Requires-Dist: pyyaml>=6.0
Requires-Dist: packaging>=23.1
Provides-Extra: recommended
Requires-Dist: scipy>=1.11.4; extra == "recommended"
Requires-Dist: matplotlib>=3.8; extra == "recommended"
Requires-Dist: opencv-python-headless>=4.5.4; extra == "recommended"
Requires-Dist: exifread>=2.3.2; extra == "recommended"
Requires-Dist: pillow-heif>=0.21.0; extra == "recommended"
Requires-Dist: astroquery>=0.4.7; extra == "recommended"
Requires-Dist: python-dateutil>=2.8.2; extra == "recommended"
Requires-Dist: photutils; extra == "recommended"
Provides-Extra: test
Requires-Dist: attrs>=19.2.0; extra == "test"
Requires-Dist: pytest-astropy-header; extra == "test"
Requires-Dist: pytest-doctestplus; extra == "test"
Requires-Dist: pytest-remotedata; extra == "test"
Requires-Dist: scipy; extra == "test"
Requires-Dist: photutils; extra == "test"
Provides-Extra: docs
Requires-Dist: sphinx; extra == "docs"
Requires-Dist: sphinx-astropy; extra == "docs"
Requires-Dist: sphinx_rtd_theme; extra == "docs"
Provides-Extra: gtk3
Requires-Dist: gobject-introspection>=1.84.0; extra == "gtk3"
Requires-Dist: pycairo>=1.27.0; extra == "gtk3"
Requires-Dist: pygobject>=3.50.0; extra == "gtk3"
Provides-Extra: gtk4
Requires-Dist: gobject-introspection>=1.84.0; extra == "gtk4"
Requires-Dist: pycairo>=1.29.0; extra == "gtk4"
Requires-Dist: pygobject>=3.54.5; extra == "gtk4"
Provides-Extra: qt5
Requires-Dist: PyQt5; extra == "qt5"
Provides-Extra: qt6
Requires-Dist: PyQt6; extra == "qt6"
Provides-Extra: pyside2
Requires-Dist: PySide2; extra == "pyside2"
Provides-Extra: pyside6
Requires-Dist: PySide6; extra == "pyside6"
Provides-Extra: tk
Requires-Dist: pycairo; extra == "tk"
Provides-Extra: web
Requires-Dist: tornado; extra == "web"
Requires-Dist: pycairo; extra == "web"
Dynamic: license-file
